apolo_apps_client/__init__.py
apolo_apps_client/_client.py
apolo_apps_client/_config.py
apolo_apps_client/_exceptions.py
apolo_apps_client/_models.py
apolo_apps_client/py.typed
apolo_apps_client-25.8.1.dist-info/LICENSE
apolo_apps_client-25.8.1.dist-info/METADATA
apolo_apps_client-25.8.1.dist-info/WHEEL
apolo_apps_client-25.8.1.dist-info/RECORD
