Metadata-Version: 2.3
Name: apolo-apps-client
Version: 25.8.1
Summary: Apolo internal client for platform-apps API
License: Proprietary
Author: apolo.us
Requires-Python: >=3.12,<4.0
Classifier: License :: Other/Proprietary License
Classifier: Programming Language :: Python :: 3
Classifier: Programming Language :: Python :: 3.12
Classifier: Programming Language :: Python :: 3.13
Requires-Dist: aiohttp (>=3.12.14,<4.0.0)
Requires-Dist: pydantic (>=2.11.7,<3.0.0)
